brunns/__init__.py
brunns/row/__init__.py
brunns/row/rowwrapper.py
brunns_row-2.1.0.dist-info/LICENSE
brunns_row-2.1.0.dist-info/METADATA
brunns_row-2.1.0.dist-info/WHEEL
brunns_row-2.1.0.dist-info/top_level.txt
brunns_row-2.1.0.dist-info/RECORD
