Metadata-Version: 2.1
Name: brunns-row
Version: 2.1.0
Summary: Convenience wrapper for DB API and csv.DictReader rows, and similar.
Home-page: https://brunns-row.readthedocs.io
Author: Simon Brunning
Author-email: simon@brunningonline.net
Classifier: Development Status :: 5 - Production/Stable
Classifier: Intended Audience :: Developers
Classifier: License :: OSI Approved :: MIT License
Classifier: Operating System :: OS Independent
Classifier: Programming Language :: Python
Classifier: Programming Language :: Python :: 3
Classifier: Programming Language :: Python :: 3.7
Classifier: Programming Language :: Python :: 3.8
Classifier: Programming Language :: Python :: 3.9
Classifier: Programming Language :: Python :: 3.10
Classifier: Programming Language :: Python :: 3.11
Classifier: Programming Language :: Python :: Implementation :: PyPy
Classifier: Topic :: Software Development :: Testing
Requires-Python: >=3.7
License-File: LICENSE
